centernet/__init__.py
centernet/config.py
centernet/data/__init__.py
centernet/data/custom_build_augmentation.py
centernet/data/custom_dataset_dataloader.py
centernet/data/datasets/__init__.py
centernet/data/datasets/coco.py
centernet/data/datasets/nuimages.py
centernet/data/datasets/objects365.py
centernet/data/transforms/__init__.py
centernet/data/transforms/custom_augmentation_impl.py
centernet/data/transforms/custom_transform.py
centernet/modeling/__init__.py
centernet/modeling/debug.py
centernet/modeling/backbone/__init__.py
centernet/modeling/backbone/bifpn.py
centernet/modeling/backbone/bifpn_fcos.py
centernet/modeling/backbone/dla.py
centernet/modeling/backbone/dlafpn.py
centernet/modeling/backbone/fpn_p5.py
centernet/modeling/backbone/res2net.py
centernet/modeling/dense_heads/__init__.py
centernet/modeling/dense_heads/centernet.py
centernet/modeling/dense_heads/centernet_head.py
centernet/modeling/dense_heads/utils.py
centernet/modeling/layers/__init__.py
centernet/modeling/layers/deform_conv.py
centernet/modeling/layers/heatmap_focal_loss.py
centernet/modeling/layers/iou_loss.py
centernet/modeling/layers/ml_nms.py
centernet/modeling/meta_arch/__init__.py
centernet/modeling/meta_arch/centernet_detector.py
centernet/modeling/roi_heads/__init__.py
centernet/modeling/roi_heads/custom_fast_rcnn.py
centernet/modeling/roi_heads/custom_roi_heads.py
centernet/modeling/roi_heads/fed_loss.py
configs/__init__.py
tools/__init__.py
tools/analyze_model.py
tools/benchmark.py
tools/convert-torchvision-to-d2.py
tools/lazyconfig_train_net.py
tools/lightning_train_net.py
tools/plain_train_net.py
tools/train_net.py
tools/visualize_data.py
tools/visualize_json_results.py
centernet_fork-0.0.2.dist-info/LICENSE
centernet_fork-0.0.2.dist-info/METADATA
centernet_fork-0.0.2.dist-info/WHEEL
centernet_fork-0.0.2.dist-info/top_level.txt
centernet_fork-0.0.2.dist-info/RECORD
